pynch/__init__.py
pynch/namedtuple_extended.py
pynch/num.py
pynch/op.py
pynch/order_conserving.py
pynch/ordered_dict.py
pynch/ordered_set.py
pynch/select.py
pynch/util.py
pynch-0.0.3.dist-info/LICENSE
pynch-0.0.3.dist-info/METADATA
pynch-0.0.3.dist-info/WHEEL
pynch-0.0.3.dist-info/top_level.txt
pynch-0.0.3.dist-info/RECORD
