Metadata-Version: 2.1
Name: pynch
Version: 0.0.3
Summary: Utils for collections and misc basic data structures.
Home-page: https://github.com/thorwhalen/newut/tree/master/pynch
Author: Thor Whalen
License: mit
Platform: any
License-File: LICENSE
